tabmat-4.2.0.dist-info/RECORD
tabmat-4.2.0.dist-info/WHEEL
tabmat-4.2.0.dist-info/top_level.txt
tabmat-4.2.0.dist-info/METADATA
tabmat-4.2.0.dist-info/licenses/LICENSE
tabmat/sparse_matrix.py
tabmat/formula.py
tabmat/constructor.py
tabmat/util.py
tabmat/categorical_matrix.py
tabmat/__init__.py
tabmat/split_matrix.py
tabmat/matrix_base.py
tabmat/dense_matrix.py
tabmat/constructor_util.py
tabmat/standardized_mat.py
tabmat/benchmark/visualize_benchmarks.py
tabmat/benchmark/memory_tools.py
tabmat/benchmark/generate_matrices.py
tabmat/benchmark/__init__.py
tabmat/benchmark/main.py
tabmat/ext/__init__.py
tabmat/ext/categorical.cpython-313-darwin.so
tabmat/ext/dense.cpython-313-darwin.so
tabmat/ext/sparse.cpython-313-darwin.so
tabmat/ext/split.cpython-313-darwin.so
tabmat/.dylibs/libc++.1.0.dylib
tabmat/.dylibs/libomp.dylib
tabmat/.dylibs/libjemalloclocal.2.dylib
